<?xml version="1.0" encoding="utf-8"?>
<vector android:height="96.0dip" android:width="96.0dip" android:viewportWidth="96.0" android:viewportHeight="96.0"
  xmlns:android="http://schemas.android.com/apk/res/android">
    <group>
        <clip-path android:pathData="M0,0h96v96h-96z" />
        <path android:fillColor="#ffffffff" android:pathData="M3.88,79.407C5.021,79.167 6.033,78.478 6.673,77.473C8.821,74.097 11.922,71.525 15.5,70.018V11C15.5,5.753 19.753,1.5 25,1.5H59C64.247,1.5 68.5,5.753 68.5,11V28.168C73.283,28.722 77.666,30.616 81.259,33.461C88.396,33.674 94.116,39.527 94.116,46.715C94.116,50.08 92.862,53.154 90.797,55.491C90.141,63.184 86.046,69.892 80.061,74.075C80.159,74.577 80.21,75.095 80.21,75.625C80.21,77.03 79.85,78.35 79.219,79.5H89C92.038,79.5 94.5,81.962 94.5,85V89C94.5,92.038 92.038,94.5 89,94.5H5C4.44,94.5 3.604,94.445 2.872,94.02C2.477,93.791 2.112,93.454 1.856,92.985C1.603,92.523 1.5,92.013 1.5,91.498V91.48V91.462V91.443V91.425V91.407V91.389V91.371V91.353V91.334V91.316V91.298V91.28V91.262V91.243V91.225V91.207V91.189V91.171V91.153V91.134V91.116V91.098V91.08V91.062V91.044V91.025V91.007V90.989V90.971V90.953V90.935V90.916V90.898V90.88V90.862V90.844V90.826V90.808V90.789V90.771V90.753V90.735V90.717V90.699V90.68V90.662V90.644V90.626V90.608V90.59V90.571V90.553V90.535V90.517V90.499V90.48V90.462V90.444V90.426V90.408V90.39V90.371V90.353V90.335V90.317V90.299V90.281V90.262V90.244V90.226V90.208V90.19V90.172V90.153V90.135V90.117V90.099V90.081V90.063V90.044V90.026V90.008V89.99V89.972V89.954V89.935V89.917V89.899V89.881V89.863V89.845V89.826V89.808V89.79V89.772V89.754V89.736V89.717V89.699V89.681V89.663V89.645V89.627V89.608V89.59V89.572V89.554V89.536V89.518V89.499V89.481V89.463V89.445V89.427V89.409V89.39V89.372V89.354V89.336V89.318V89.299V89.281V89.263V89.245V89.227V89.209V89.19V89.172V89.154V89.136V89.118V89.1V89.081V89.063V89.045V89.027V89.009V88.991V88.973V88.954V88.936V88.918V88.9V88.882V88.864V88.845V88.827V88.809V88.791V88.773V88.755V88.736V88.718V88.7V88.682V88.664V88.646V88.627V88.609V88.591V88.573V88.555V88.536V88.518V88.5V88.482V88.464V88.446V88.427V88.409V88.391V88.373V88.355V88.337V88.318V88.3V88.282V88.264V88.246V88.228V88.209V88.191V88.173V88.155V88.137V88.119V88.1V88.082V88.064V88.046V88.028V88.01V87.991V87.973V87.955V87.937V87.919V87.901V87.882V87.864V87.846V87.828V87.81V87.792V87.773V87.755V87.737V87.719V87.701V87.683V87.664V87.646V87.628V87.61V87.592V87.574V87.555V87.537V87.519V87.501V87.483V87.465V87.446V87.428V87.41V87.392V87.374V87.355V87.337V87.319V87.301V87.283V87.265V87.246V87.228V87.21V87.192V87.174V87.156V87.137V87.119V87.101V87.083V87.065V87.047V87.029V87.01V86.992V86.974V86.956V86.938V86.92V86.901V86.883V86.865V86.847V86.829V86.811V86.792V86.774V86.756V86.738V86.72V86.701V86.683V86.665V86.647V86.629V86.611V86.592V86.574V86.556V86.538V86.52V86.502V86.483V86.465V86.447V86.429V86.411V86.393V86.374V86.356V86.338V86.32V86.302V86.284V86.265V86.247V86.229V86.211V86.193V86.175V86.156V86.138V86.12V86.102V86.084V86.066V86.047V86.029V86.011V85.993V85.975V85.957V85.938V85.92V85.902V85.884V85.866V85.848V85.829V85.811V85.793V85.775V85.757V85.739V85.72V85.702V85.684V85.666V85.648V85.63V85.611V85.593V85.575V85.557V85.539V85.521V85.502V85.484V85.466V85.448V85.43V85.411V85.393V85.375V85.357V85.339V85.321V85.302V85.284V85.266V85.248V85.23V85.212V85.193V85.175V85.157V85.139V85.121V85.103V85.085V85.066V85.048V85.03V85.012V84.994V84.976V84.957V84.939V84.921V84.903V84.885V84.867V84.848V84.83V84.812V84.794V84.776V84.757V84.739V84.721V84.703V84.685V84.667V84.648V84.63V84.612V84.594V84.576V84.558V84.539V84.521V84.503V84.485V84.467V84.449V84.43V84.412V84.394V84.376V84.358V84.34V84.321V84.303V84.285V84.267V84.249V84.231V84.212V84.194V84.176V84.158V84.14V84.122V84.103V84.085V84.067V84.049V84.031V84.013V83.994V83.976V83.958V83.94V83.922V83.904V83.885V83.867V83.849V83.831V83.813V83.795V83.776V83.758V83.74V83.722V83.704V83.686V83.667V83.649V83.631V83.613V83.595V83.576V83.558V83.54V83.522V83.504V83.486V83.467V83.449V83.431V83.413V83.395V83.377V83.358V83.34V83.322V83.304V83.286V83.268V83.249V83.231V83.213V83.195V83.177V83.159V83.141V83.122V83.104V83.086V83.068V83.05V83.032V83.013V82.995V82.977V82.959V82.941V82.923V82.904V82.886V82.868V82.85V82.832V82.813V82.795V82.777V82.759V82.741V82.723V82.704V82.686V82.668V82.65V82.632V82.614V82.595V82.577V82.559V82.541V82.523V82.505V82.487V82.468V82.45V82.432V82.414V82.396V82.377V82.359V82.341V82.323V82.305V82.287V82.268V82.25V82.232V82.214V82.196C1.5,80.651 2.723,79.649 3.88,79.407ZM3.88,79.407L4.188,80.874L3.88,79.407Z" android:strokeColor="#ffffffff" android:strokeWidth="3.0" android:strokeLineCap="round" />
        <path android:fillColor="#ff4e00aa" android:pathData="M20,75H11V90H20V75Z" />
        <path android:fillColor="#ff4e00aa" android:pathData="M34,82H26V84H34V82Z" />
        <path android:fillColor="#ffac64ff" android:pathData="M5,89.863C9.298,89.274 13.166,86.827 15.531,83.111C17.16,80.55 19.985,79 23.019,79H25.5V73H23.019C17.933,73 13.2,75.599 10.469,79.889C9.209,81.869 7.234,83.245 5,83.767V89.863Z" />
        <path android:fillColor="#ff55595e" android:pathData="M17,11C17,6.582 20.582,3 25,3H59C63.418,3 67,6.582 67,11V85C67,89.418 63.418,93 59,93H25C22.474,93 20.221,91.829 18.755,90H20V75H17V11ZM51.943,57.164C46.181,57.164 41.495,52.477 41.495,46.716C41.495,40.955 46.181,36.268 51.943,36.268C57.703,36.268 62.39,40.955 62.39,46.716C62.39,52.477 57.703,57.164 51.943,57.164ZM26,82H34V84H26V82Z" android:fillType="evenOdd" />
        <path android:fillColor="#ff3c4043" android:pathData="M26,9C24.343,9 23,10.343 23,12V74C23,75.657 24.343,77 26,77H58C59.657,77 61,75.657 61,74V51.92C59.194,55.051 55.81,57.164 51.943,57.164C46.181,57.164 41.495,52.477 41.495,46.716C41.495,40.955 46.181,36.268 51.943,36.268C55.81,36.268 59.194,38.381 61,41.512V12C61,10.343 59.657,9 58,9H26Z" />
        <path android:fillColor="#ff963eff" android:pathData="M67,84H89C89.552,84 90,84.448 90,85V89C90,89.552 89.552,90 89,90H67V84Z" />
        <path android:fillColor="#ffac64ff" android:pathData="M28.481,79H26V73H28.481C33.567,73 38.3,75.599 41.031,79.889C42.66,82.45 45.485,84 48.519,84H64.5C65.052,84 65.5,84.448 65.5,85V89C65.5,89.552 65.052,90 64.5,90H48.519C43.433,90 38.7,87.401 35.969,83.111C34.34,80.55 31.515,79 28.481,79Z" android:fillType="evenOdd" />
        <path android:fillColor="#ff711ed4" android:pathData="M28.484,73C33.57,73 38.304,75.599 41.035,79.889C42.664,82.45 45.488,84 48.523,84H64.504C65.056,84 65.504,84.448 65.504,85V89C65.504,89.552 65.056,90 64.504,90H89.004C89.556,90 90.004,89.552 90.004,89V85C90.004,84.448 89.556,84 89.004,84H75.523C72.488,84 69.664,82.45 68.035,79.889C65.304,75.599 60.57,73 55.484,73H28.484Z" />
        <path android:fillColor="@*android:color/accent_material_dark" android:pathData="M43.278,52.548C43.269,52.802 43.265,53.057 43.265,53.313V57.25C43.264,59.918 41.16,62.468 38,62.485C37.978,65.063 44.582,75.596 57.704,75.62L65.577,75.625C77.515,75.625 87.263,66.25 87.861,54.461C86.006,56.14 83.548,57.164 80.856,57.164C75.095,57.164 70.408,52.477 70.408,46.716C70.408,41.245 74.635,36.743 79.994,36.303C76.102,32.998 71.066,31 65.577,31C60.072,31 55.033,32.994 51.141,36.299C51.406,36.278 51.673,36.268 51.943,36.268C57.703,36.268 62.39,40.955 62.39,46.716C62.39,52.477 57.703,57.164 51.943,57.164C48.339,57.164 45.157,55.331 43.278,52.548Z" />
        <path android:fillColor="#ff000000" android:pathData="M62.375,61.294C61.547,61.294 60.875,61.965 60.875,62.794C60.875,63.622 61.547,64.294 62.375,64.294H70.29C71.119,64.294 71.79,63.622 71.79,62.794C71.79,61.965 71.119,61.294 70.29,61.294H62.375Z" />
        <path android:fillColor="#ff000000" android:pathData="M58.561,48.055C58.561,49.504 57.386,50.68 55.936,50.68C54.487,50.68 53.311,49.504 53.311,48.055C53.311,46.605 54.487,45.43 55.936,45.43C57.386,45.43 58.561,46.605 58.561,48.055Z" />
        <path android:fillColor="#ff000000" android:pathData="M76.967,50.68C78.417,50.68 79.592,49.504 79.592,48.055C79.592,46.605 78.417,45.43 76.967,45.43C75.517,45.43 74.342,46.605 74.342,48.055C74.342,49.504 75.517,50.68 76.967,50.68Z" />
        <path android:fillColor="#ff000000" android:pathData="M67,11V29.542C72.192,29.85 76.944,31.833 80.722,34.956C80.755,34.956 80.788,34.955 80.821,34.955L80.856,34.955C87.351,34.955 92.616,40.22 92.616,46.715C92.616,49.876 91.369,52.746 89.34,54.859C88.84,62.672 84.571,69.46 78.332,73.425C78.576,74.112 78.71,74.853 78.71,75.625C78.71,77.848 77.604,79.813 75.913,81H89C91.209,81 93,82.791 93,85V89C93,91.209 91.209,93 89,93H5C4,93 3,92.762 3,91.498C3,90.67 3.672,90.007 4.496,89.923C8.994,89.463 13.074,86.972 15.531,83.11C15.948,82.455 16.443,81.866 17,81.352V74.272C14.357,75.442 12.069,77.375 10.469,79.889C9.17,81.93 7.111,83.33 4.791,83.813C3.817,84.016 3,83.191 3,82.196C3,81.535 3.54,81.01 4.188,80.874C5.72,80.553 7.08,79.628 7.938,78.278C10.102,74.878 13.312,72.363 17,71.043V11C17,6.582 20.582,3 25,3H59C63.418,3 67,6.582 67,11ZM25,6H59C61.761,6 64,8.239 64,11V29.551C62.981,29.618 61.98,29.749 61,29.94V12C61,10.343 59.657,9 58,9H26C24.343,9 23,10.343 23,12V84C23,85.657 24.343,87 26,87H35.158C36.181,88.151 37.342,89.157 38.607,90H25C22.239,90 20,87.761 20,85V11C20,8.239 22.239,6 25,6ZM44.797,89.527C45.998,89.838 47.248,90 48.519,90H64.5C65.052,90 65.5,89.552 65.5,89V85C65.5,84.448 65.052,84 64.5,84H48.519C45.485,84 42.66,82.45 41.031,79.889C38.394,75.745 33.888,73.179 29,73.009C28.827,73.003 28.654,73 28.481,73H26V79H28.481C31.515,79 34.34,80.55 35.969,83.111C38.017,86.329 41.192,88.595 44.797,89.527ZM38.393,73C40.435,74.36 42.204,76.145 43.562,78.279C44.64,79.974 46.51,81 48.519,81H49.996C48.308,79.813 47.205,77.85 47.205,75.629C47.205,75.327 47.226,75.031 47.265,74.74C46.194,74.215 45.204,73.627 44.294,73H38.393ZM40.753,70C39.566,68.772 38.628,67.529 37.942,66.401C37.494,65.664 37.143,64.959 36.901,64.324C36.669,63.717 36.495,63.067 36.5,62.472C36.507,61.652 37.172,60.99 37.992,60.985C40.257,60.973 41.764,59.164 41.765,57.25V53.313C41.765,53.084 41.768,52.856 41.774,52.628C40.762,50.891 40.182,48.871 40.182,46.715C40.182,40.789 44.566,35.887 50.267,35.074C52.526,33.176 55.142,31.69 58,30.731V12H26V70H40.753ZM32.897,84C31.791,82.74 30.186,82 28.481,82H26V84H32.897ZM68.374,90H89C89.552,90 90,89.552 90,89V85C90,84.448 89.552,84 89,84C82.125,84 75.249,83.984 68.374,84C68.456,84.32 68.5,84.655 68.5,85V89C68.5,89.345 68.456,89.68 68.374,90ZM17.077,86.117C17.281,87.574 17.877,88.905 18.755,90H12.893C14.472,88.948 15.888,87.642 17.077,86.117ZM55.032,35.365C59.582,36.601 63.036,40.5 63.617,45.284H69.182C69.715,40.889 72.672,37.242 76.677,35.719C73.461,33.681 69.653,32.5 65.577,32.5C61.729,32.5 58.125,33.544 55.032,35.365ZM86.01,57.289C84.454,58.049 82.705,58.476 80.856,58.476C74.893,58.476 69.966,54.038 69.199,48.284H63.599C62.832,54.038 57.905,58.476 51.942,58.476C49.24,58.476 46.751,57.564 44.765,56.032V57.25C44.764,60.106 42.882,62.872 39.901,63.721C40.056,64.055 40.257,64.433 40.506,64.842C41.25,66.067 42.39,67.513 43.926,68.895C45.154,70 46.627,71.057 48.348,71.928C49.53,70.2 51.516,69.066 53.768,69.066C56.89,69.066 59.503,71.247 60.167,74.168L65.209,74.171C65.329,74.14 65.453,74.125 65.577,74.125C75.712,74.125 84.155,66.881 86.01,57.289ZM60.16,77.121C59.789,78.715 58.837,80.087 57.54,81H68.382C67.083,80.088 66.129,78.718 65.757,77.124L60.16,77.121ZM51.942,37.58C56.979,37.58 61.077,41.679 61.077,46.716C61.077,51.753 56.979,55.851 51.942,55.851C46.905,55.851 42.807,51.753 42.807,46.716C42.807,41.679 46.905,37.58 51.942,37.58ZM89.991,46.716C89.991,41.679 85.893,37.58 80.856,37.58C75.819,37.58 71.721,41.679 71.721,46.716C71.721,51.753 75.819,55.851 80.856,55.851C85.893,55.851 89.991,51.753 89.991,46.716Z" android:fillType="evenOdd" />
    </group>
</vector>